{
  "project_info": {
    "project_number": "460954131904",
    "project_id": "life-362114",
    "storage_bucket": "life-362114.appspot.com"
  },
  "client": [
    {
      "client_info": {
        "mobilesdk_app_id": "1:460954131904:android:da88d62b0d2ba9777dfc25",
        "android_client_info": {
          "package_name": "ru.bmstu.ulife"
        }
      },
      "oauth_client": [
        {
          "client_id": "460954131904-s52vs8nn0d7llaj9p9kpka1hku05m5mu.apps.googleusercontent.com",
          "client_type": 3
        }
      ],
      "api_key": [
        {
          "current_key": "AIzaSyDwaipGvdBD--mzU4dod0dRZl5nDfn1Lgc"
        }
      ],
      "services": {
        "appinvite_service": {
          "other_platform_oauth_client": [
            {
              "client_id": "460954131904-s52vs8nn0d7llaj9p9kpka1hku05m5mu.apps.googleusercontent.com",
              "client_type": 3
            }
          ]
        }
      }
    }
  ],
  "configuration_version": "1"
}